{
    "fyros": {
        "name": "Fyros",
        "member": "Fyros"
    },
    "matis": {
        "name": "Matis",
        "member": "Matis"
    },
    "tryker": {
        "name": "Tryker",
        "member": "Tryker"
    },
    "zorai": {
        "name": "Zoraï",
        "member": "Zoraï"
    },
    "bandit": {
        "name": "Banditen",
        "member": "Banditen"
    },
    "civil": {
        "name": "Zivilisten",
        "member": "Zivilisten"
    },
    "degen": {
        "name": "Verrückter Stamm",
        "member": "Verrückten"
    },
    "fauna": {
        "name": "Fauna",
        "member": "Fauna"
    },
    "fauna_carnivore": {
        "name": "Fleischfressende Fauna",
        "member": "Fleischfresser"
    },
    "fauna_herbivore": {
        "name": "Pflanzenfressende Fauna",
        "member": "Pflanzenfresser"
    },
    "flora": {
        "name": "Flora",
        "member": "Flora"
    },
    "goo": {
        "name": "Goo",
        "member": "Goo"
    },
    "kami": {
        "name": "Kami",
        "member": "Kamis"
    },
    "karavan": {
        "name": "Karavan",
        "member": "Karavan"
    },
    "kitin": {
        "name": "Kitin",
        "member": "Kitin"
    },
    "tribe_ancient_dryads": {
        "name": "Alte Dryaden",
        "member": "Mitglieder der Alten Dryaden"
    },
    "tribe_antikamis": {
        "name": "Antikami",
        "member": "Antikami"
    },
    "tribe_barkers": {
        "name": "Rindengräber",
        "member": "Rindengräber"
    },
    "tribe_beachcombers": {
        "name": "Gischtläufer",
        "member": "Gischtläufer"
    },
    "tribe_black_circle": {
        "name": "Schwarze Kreis",
        "member": "Mitglieder des Schwarzen Kreis"
    },
    "tribe_cholorogoos": {
        "name": "Chlorogoos",
        "member": "Chlorogoos"
    },
    "tribe_cockroaches": {
        "name": "Kakerlaken",
        "member": "Mitglieder der Kakerlaken"
    },
    "tribe_company_of_the_eternal_tree": {
        "name": "Gemeinschaft des Ewigen Baumes",
        "member": "Mitglieder des Ewigen Baumes"
    },
    "tribe_corsair": {
        "name": "Korsaren",
        "member": "Mitglieder der Korsaren"
    },
    "tribe_cute": {
        "name": "Cuzane",
        "member": "Cuzane"
    },
    "tribe_darkening_sap": {
        "name": "Matiagoo",
        "member": "Matiagoo"
    },
    "tribe_dune_riders": {
        "name": "Dünenreiter",
        "member": "Dünenreiter"
    },
    "tribe_ecowarriors": {
        "name": "Ökokrieger",
        "member": "Ökokrieger"
    },
    "tribe_firebrands": {
        "name": "Blutrünstige",
        "member": "Mitglieder der Blutrünstigen"
    },
    "tribe_first_deserter": {
        "name": "Erste Deserteure",
        "member": "Mitglieder der Ersten Deserteure"
    },
    "tribe_frahar": {
        "name": "Fraiders",
        "member": "Fraider"
    },
    "tribe_frahar_hunters": {
        "name": "Fraharjäger",
        "member": "Fraharjäger"
    },
    "tribe_gibbay": {
        "name": "Gibads",
        "member": "Gibad"
    },
    "tribe_goo_heads": {
        "name": "Erleuchtete des Goos",
        "member": "Mitglieder der Erleuchteten des Goos"
    },
    "tribe_green_seed": {
        "name": "Grünen Samen",
        "member": "Mitglieder der Grünen Samen"
    },
    "tribe_hamazans_of_the_dead_seed": {
        "name": "Matis-Amazonen",
        "member": "Matis-Amazonen"
    },
    "tribe_icon_workshipers": {
        "name": "Ikonenschnitzer",
        "member": "Ikonenschnitzer"
    },
    "tribe_keepers": {
        "name": "Erinnerer",
        "member": "Erinnerer"
    },
    "tribe_kitin_gatheres": {
        "name": "Kitin-Jäger",
        "member": "Kitin-Jäger"
    },
    "tribe_lagoon_brothers": {
        "name": "Lagunenbrüder",
        "member": "Lagunenbrüder"
    },
    "tribe_lawless": {
        "name": "Gesetzlose",
        "member": "Mitglieder der Gesetzlosen"
    },
    "tribe_leviers": {
        "name": "Zöllner",
        "member": "Zöllner"
    },
    "tribe_master_of_the_goo": {
        "name": "Meister des Goo",
        "member": "Meister des Goo"
    },
    "tribe_matisian_border_guards": {
        "name": "Matisianische Grenzwächter",
        "member": "Mitglieder der Matisianischen Grenzwächter"
    },
    "tribe_night_turners": {
        "name": "Nachtwender",
        "member": "Nachtwender"
    },
    "tribe_oasis_diggers": {
        "name": "Brunnengräber",
        "member": "Brunnengräber"
    },
    "tribe_pyromancers": {
        "name": "Feuermagierinnen",
        "member": "Feuermagierinnen"
    },
    "tribe_recoverers": {
        "name": "Recycler",
        "member": "Recycler"
    },
    "tribe_renegades": {
        "name": "Abtrünnigen",
        "member": "Mitglieder der Abtrünnigen"
    },
    "tribe_restorers": {
        "name": "Aufpasser",
        "member": "Aufpasser"
    },
    "tribe_root_tappers": {
        "name": "Unterwasserwurzel-Extrahierer",
        "member": "Unterwasserwurzel-Extrahierer"
    },
    "tribe_sacred_sap": {
        "name": "Heiliges Sap",
        "member": "Mitglieder des Heiligen Saps"
    },
    "tribe_sap_gleaners": {
        "name": "Sapsammler",
        "member": "Sapsammler"
    },
    "tribe_sap_slaves": {
        "name": "Sapsklaven",
        "member": "Sapsklaven"
    },
    "tribe_scorchers": {
        "name": "Enthäutete",
        "member": "Mitglieder der Enthäuteten"
    },
    "tribe_shadow_runners": {
        "name": "Schattenschmuggler",
        "member": "Schattenschmuggler"
    },
    "tribe_siblings_of_the_weeds": {
        "name": "Geschwister der Pflanzen",
        "member": "Mitglieder der Geschwister der Pflanzen"
    },
    "tribe_silt_sculptors": {
        "name": "Lehmbildhauer",
        "member": "Lehmbildhauer"
    },
    "tribe_slavers": {
        "name": "Sklaventreiber",
        "member": "Sklaventreiber"
    },
    "tribe_smuglers": {
        "name": "Schmuggler",
        "member": "Schmuggler"
    },
    "tribe_the_arid_matis": {
        "name": "Dörre Matis",
        "member": "Mitglieder von Dörre Matis"
    },
    "tribe_the_kuilde": {
        "name": "Kuilde",
        "member": "Mitglieder der Kuilde"
    },
    "tribe_the_slash_and_burn": {
        "name": "Scharlachrote Söldner",
        "member": "Mitglieder der Scharlachroten Söldner"
    },
    "tribe_tutors": {
        "name": "Tutoren",
        "member": "Mitglieder der Tutoren"
    },
    "tribe_water_breakers": {
        "name": "Wasserbrecher",
        "member": "Wasserbrecher"
    },
    "tribe_woven_bridles": {
        "name": "Wüstenplünderer",
        "member": "Wüstenplünderer"
    }
}